odoo9_addon_website_sale_product_brand-9.0.1.1.1-py2.7-nspkg.pth
odoo9_addon_website_sale_product_brand-9.0.1.1.1.dist-info/DESCRIPTION.rst
odoo9_addon_website_sale_product_brand-9.0.1.1.1.dist-info/METADATA
odoo9_addon_website_sale_product_brand-9.0.1.1.1.dist-info/RECORD
odoo9_addon_website_sale_product_brand-9.0.1.1.1.dist-info/WHEEL
odoo9_addon_website_sale_product_brand-9.0.1.1.1.dist-info/metadata.json
odoo9_addon_website_sale_product_brand-9.0.1.1.1.dist-info/namespace_packages.txt
odoo9_addon_website_sale_product_brand-9.0.1.1.1.dist-info/top_level.txt
odoo_addons/website_sale_product_brand/README.rst
odoo_addons/website_sale_product_brand/__init__.py
odoo_addons/website_sale_product_brand/__openerp__.py
odoo_addons/website_sale_product_brand/controllers/__init__.py
odoo_addons/website_sale_product_brand/controllers/main.py
odoo_addons/website_sale_product_brand/data/website_menu.xml
odoo_addons/website_sale_product_brand/i18n/ar.po
odoo_addons/website_sale_product_brand/i18n/bg.po
odoo_addons/website_sale_product_brand/i18n/bs.po
odoo_addons/website_sale_product_brand/i18n/ca.po
odoo_addons/website_sale_product_brand/i18n/cs.po
odoo_addons/website_sale_product_brand/i18n/da.po
odoo_addons/website_sale_product_brand/i18n/de.po
odoo_addons/website_sale_product_brand/i18n/el_GR.po
odoo_addons/website_sale_product_brand/i18n/en_GB.po
odoo_addons/website_sale_product_brand/i18n/es.po
odoo_addons/website_sale_product_brand/i18n/es_AR.po
odoo_addons/website_sale_product_brand/i18n/es_CL.po
odoo_addons/website_sale_product_brand/i18n/es_CO.po
odoo_addons/website_sale_product_brand/i18n/es_CR.po
odoo_addons/website_sale_product_brand/i18n/es_DO.po
odoo_addons/website_sale_product_brand/i18n/es_EC.po
odoo_addons/website_sale_product_brand/i18n/es_MX.po
odoo_addons/website_sale_product_brand/i18n/es_PE.po
odoo_addons/website_sale_product_brand/i18n/et.po
odoo_addons/website_sale_product_brand/i18n/eu.po
odoo_addons/website_sale_product_brand/i18n/fa.po
odoo_addons/website_sale_product_brand/i18n/fi.po
odoo_addons/website_sale_product_brand/i18n/fr.po
odoo_addons/website_sale_product_brand/i18n/he.po
odoo_addons/website_sale_product_brand/i18n/hr.po
odoo_addons/website_sale_product_brand/i18n/hr_HR.po
odoo_addons/website_sale_product_brand/i18n/hu.po
odoo_addons/website_sale_product_brand/i18n/id.po
odoo_addons/website_sale_product_brand/i18n/it.po
odoo_addons/website_sale_product_brand/i18n/ja.po
