Metadata-Version: 2.0
Name: odoo9-addon-website-sale-product-brand
Version: 9.0.1.1.1
Summary: Product Brand Filtering in Website
Home-page: http://www.serpentcs.com
Author: Serpent Consulting Services Pvt. Ltd.,Odoo Community Association (OCA)
Author-email: support@odoo-community.org
License: AGPL-3
Platform: UNKNOWN
Classifier: Programming Language :: Python
Classifier: Framework :: Odoo
Classifier: License :: OSI Approved :: GNU Affero General Public License v3
Requires-Python: ~=2.7
Requires-Dist: odoo (<9.1a,>=9.0a)
Requires-Dist: odoo9-addon-product-brand
